ci_watson/__init__.py
ci_watson/artifactory_helpers.py
ci_watson/hst_helpers.py
ci_watson/jwst_helpers.py
ci_watson/plugin.py
ci_watson/resource_tracker.py
ci_watson/version.py
ci_watson/scripts/okify_regtests.py
ci_watson-0.10.0.dist-info/licenses/LICENSE.md
ci_watson-0.10.0.dist-info/METADATA
ci_watson-0.10.0.dist-info/WHEEL
ci_watson-0.10.0.dist-info/entry_points.txt
ci_watson-0.10.0.dist-info/top_level.txt
ci_watson-0.10.0.dist-info/RECORD
